odoo/addons/product_harmonized_system_country/README.rst
odoo/addons/product_harmonized_system_country/__init__.py
odoo/addons/product_harmonized_system_country/__manifest__.py
odoo/addons/product_harmonized_system_country/models/__init__.py
odoo/addons/product_harmonized_system_country/models/hs_code.py
odoo/addons/product_harmonized_system_country/models/hs_code_country.py
odoo/addons/product_harmonized_system_country/models/product_product.py
odoo/addons/product_harmonized_system_country/readme/CONFIGURE.rst
odoo/addons/product_harmonized_system_country/readme/CONTRIBUTORS.rst
odoo/addons/product_harmonized_system_country/readme/DESCRIPTION.rst
odoo/addons/product_harmonized_system_country/security/ir.model.access.csv
odoo/addons/product_harmonized_system_country/static/description/icon.png
odoo/addons/product_harmonized_system_country/static/description/index.html
odoo/addons/product_harmonized_system_country/tests/__init__.py
odoo/addons/product_harmonized_system_country/tests/test_product_hamonized_system_country.py
odoo/addons/product_harmonized_system_country/views/hs_code.xml
odoo_addon_product_harmonized_system_country-16.0.1.0.0.dist-info/METADATA
odoo_addon_product_harmonized_system_country-16.0.1.0.0.dist-info/WHEEL
odoo_addon_product_harmonized_system_country-16.0.1.0.0.dist-info/top_level.txt
odoo_addon_product_harmonized_system_country-16.0.1.0.0.dist-info/RECORD
