Metadata-Version: 2.1
Name: odoo-addon-product_harmonized_system_country
Version: 16.0.1.0.0
Summary: Specific HS Code for given countries
Home-page: https://github.com/sygel-technology/sy-intrastat-extrastat
Author: Sygel, Odoo Community Association (OCA)
Author-email: support@odoo-community.org
License: AGPL-3
Classifier: Programming Language :: Python
Classifier: Framework :: Odoo
Classifier: Framework :: Odoo :: 16.0
Classifier: License :: OSI Approved :: GNU Affero General Public License v3
Requires-Python: >=3.10
Requires-Dist: odoo-addon-product-harmonized-system<16.1dev,>=16.0dev
Requires-Dist: odoo<16.1dev,>=16.0a
